vision_mlp_oneflow/__init__.py
vision_mlp_oneflow/gmlp.py
vision_mlp_oneflow/mlp_mixer.py
vision_mlp_oneflow/resmlp.py
vision_mlp_oneflow/vip.py
vision_mlp_oneflow-0.0.2.dist-info/LICENSE
vision_mlp_oneflow-0.0.2.dist-info/METADATA
vision_mlp_oneflow-0.0.2.dist-info/WHEEL
vision_mlp_oneflow-0.0.2.dist-info/top_level.txt
vision_mlp_oneflow-0.0.2.dist-info/RECORD
