Metadata-Version: 2.1
Name: vision-mlp-oneflow
Version: 0.0.2
Summary: vision mlp model based on oneflow
Home-page: https://github.com/rentainhe/vision-mlp-oneflow.git
Author: Ren Tianhe
Author-email: 596106517@qq.com
License: UNKNOWN
Platform: UNKNOWN
Classifier: Programming Language :: Python :: 3
Classifier: License :: OSI Approved :: MIT License
Classifier: Operating System :: OS Independent
License-File: LICENSE
